signature_extraction/__init__.py
signature_extraction/event_signature_extraction.py
signature_extraction/flow_grouping.py
signature_extraction/pkt_extraction.py
signature_extraction/application_layer/ApplicationLayer.py
signature_extraction/application_layer/CoAP.py
signature_extraction/application_layer/DHCP.py
signature_extraction/application_layer/DNS.py
signature_extraction/application_layer/HTTP.py
signature_extraction/application_layer/__init__.py
signature_extraction/network/FlowFingerprint.py
signature_extraction/network/NetworkPattern.py
signature_extraction/network/Packet.py
signature_extraction/network/__init__.py
signature_extraction/utils/__init__.py
signature_extraction/utils/distance.py
signature_extraction/utils/packet_utils.py
signature_extraction-1.0.9.dist-info/licenses/LICENSE
signature_extraction-1.0.9.dist-info/METADATA
signature_extraction-1.0.9.dist-info/WHEEL
signature_extraction-1.0.9.dist-info/top_level.txt
signature_extraction-1.0.9.dist-info/RECORD
