Metadata-Version: 2.4
Name: signature-extraction
Version: 1.0.9
Summary: Extract signatures from IoT event network traffic
Author-email: François De Keersmaeker <francois.dekeersmaeker+github@proton.me>
Maintainer-email: François De Keersmaeker <francois.dekeersmaeker+github@proton.me>
License-Expression: GPL-3.0-or-later
Project-URL: Homepage, https://github.com/smart-home-network-security/signature-extraction
Project-URL: Source, https://github.com/smart-home-network-security/signature-extraction
Keywords: network,traffic,fingerprinting,firewall
Classifier: Development Status :: 3 - Alpha
Classifier: Programming Language :: Python :: 3
Classifier: Programming Language :: Python :: 3.8
Classifier: Programming Language :: Python :: 3.9
Classifier: Programming Language :: Python :: 3.10
Classifier: Programming Language :: Python :: 3.11
Classifier: Programming Language :: Python :: 3.12
Classifier: Programming Language :: Python :: 3 :: Only
Classifier: Operating System :: OS Independent
Requires-Python: >=3.8
License-File: LICENSE
Requires-Dist: cryptography==45.0.6
Requires-Dist: scapy==2.6.1
Requires-Dist: pandas==2.3.2
Requires-Dist: Levenshtein==0.27.1
Requires-Dist: dns-unbound-cache-reader
Requires-Dist: profile-translator-blocklist
Dynamic: license-file
